readable_reprs/__init__.py
readable_reprs-0.1.2.dist-info/METADATA
readable_reprs-0.1.2.dist-info/WHEEL
readable_reprs-0.1.2.dist-info/licenses/LICENSE.txt
readable_reprs-0.1.2.dist-info/sboms/bom.json
readable_reprs-0.1.2.dist-info/RECORD
