Metadata-Version: 2.4
Name: readable-reprs
Version: 0.1.2
Summary: Make stdlib reprs evaluatable
Project-URL: homepage, https://github.com/Tom01098/readable-reprs
Project-URL: source, https://github.com/Tom01098/readable-reprs
Project-URL: changelog, https://github.com/Tom01098/readable-reprs/blob/main/CHANGELOG.md
License-Expression: MIT
License-File: LICENSE.txt
Requires-Python: >=3.8
